{
  "project_info": {
    "project_number": "1090547724167",
    "firebase_url": "https://pentref-ccf8e.firebaseio.com",
    "project_id": "pentref-ccf8e",
    "storage_bucket": "pentref-ccf8e.appspot.com"
  },
  "client": [
    {
      "client_info": {
        "mobilesdk_app_id": "1:1090547724167:android:5650ea4dc7282387",
        "android_client_info": {
          "package_name": "com.ywca.pentref"
        }
      },
      "oauth_client": [
        {
          "client_id": "1090547724167-d0etp27jg0rca6asd5vb8gged1p3hucq.apps.googleusercontent.com",
          "client_type": 1,
          "android_info": {
            "package_name": "com.ywca.pentref",
            "certificate_hash": "c06ceb1b8a29c1804c9462771f5b77146eff3bd2"
          }
        },
        {
          "client_id": "1090547724167-0utf6p6diiphk11r1sgarr4mdgl0lho9.apps.googleusercontent.com",
          "client_type": 1,
          "android_info": {
            "package_name": "com.ywca.pentref",
            "certificate_hash": "7fa3060d38c8bc00405ce8c2821825a93d33032e"
          }
        },
        {
          "client_id": "1090547724167-7qojv06bm5cedjjbkdrhspaovcdagr1n.apps.googleusercontent.com",
          "client_type": 1,
          "android_info": {
            "package_name": "com.ywca.pentref",
            "certificate_hash": "7755467603ca0255d0c3d0d1b41776e662abf1dd"
          }
        },
        {
          "client_id": "1090547724167-jb7bc3191eko1v0pkuete2425curaj80.apps.googleusercontent.com",
          "client_type": 3
        }
      ],
      "api_key": [
        {
          "current_key": "AIzaSyD8X4FhyJTLbExsMbNQ6-nQSTLHnddCR0U"
        }
      ],
      "services": {
        "analytics_service": {
          "status": 1
        },
        "appinvite_service": {
          "status": 2,
          "other_platform_oauth_client": [
            {
              "client_id": "1090547724167-jb7bc3191eko1v0pkuete2425curaj80.apps.googleusercontent.com",
              "client_type": 3
            }
          ]
        },
        "ads_service": {
          "status": 2
        }
      }
    }
  ],
  "configuration_version": "1"
}